odoo/addons/ssi_timesheet_attendance_work_log/README.rst
odoo/addons/ssi_timesheet_attendance_work_log/__init__.py
odoo/addons/ssi_timesheet_attendance_work_log/__manifest__.py
odoo/addons/ssi_timesheet_attendance_work_log/models/__init__.py
odoo/addons/ssi_timesheet_attendance_work_log/models/hr_timesheet.py
odoo/addons/ssi_timesheet_attendance_work_log/models/hr_timesheet_daily_summary.py
odoo/addons/ssi_timesheet_attendance_work_log/models/hr_work_log.py
odoo/addons/ssi_timesheet_attendance_work_log/static/description/icon.png
odoo/addons/ssi_timesheet_attendance_work_log/static/description/icon_timesheet.png
odoo/addons/ssi_timesheet_attendance_work_log/views/hr_timesheet_views.xml
odoo14_addon_ssi_timesheet_attendance_work_log-14.0.1.3.0.dist-info/METADATA
odoo14_addon_ssi_timesheet_attendance_work_log-14.0.1.3.0.dist-info/WHEEL
odoo14_addon_ssi_timesheet_attendance_work_log-14.0.1.3.0.dist-info/top_level.txt
odoo14_addon_ssi_timesheet_attendance_work_log-14.0.1.3.0.dist-info/RECORD
